[{"source": "https://www.money.pl", "title": "Niemieccy rolnicy maj\u0105 do\u015b\u0107. Protestowali przeciwko polityce klimatycznej UE - Money.pl", "description": "Niemieccy rolnicy maj\u0105 do\u015b\u0107. Protestowali przeciwko polityce klimatycznej UE - Money.pl", "link": "https://www.money.pl/gospodarka/niemieccy-rolnicy-maja-dosc-protestowali-przeciwko-polityce-klimatycznej-ue-6807430977067520a.html", "date_published": "2022-08-31 20:53:45+00:00", "persistent": true, "user": "rumpel", "language": "pl-PL", "tags": ["germany", "agriculture"]}]