[{"source": "https://www.youtube.com/feeds/videos.xml?channel_id=UC7v3-2K1N84V67IF-WTRG-Q", "title": "Obi-Wan Kenobi: Episode 1 & 2 - Review", "description": "Go to http://athleticgreens.com/jahns & get a special offer of Vitamin D + 5 Travel Packs for those who subscribe to AG1!\nThank you to Athletic Greens for sponsoring!\n\nThe first 2 episodes of Obi-Wan Kenobi are out! Do they live up to the 45 year long hype? Here are my thoughts.", "link": "https://www.youtube.com/watch?v=SfJnmodbFg4", "date_published": "2022-05-27 00:00:00+00:00", "persistent": false, "user": null, "language": "en-US"}]