[{"source": "https://www.youtube.com/feeds/videos.xml?channel_id=UCNvzD7Z-g64bPXxGzaQaa4g", "title": "10 Games With MIND-BLOWING LORE", "description": "Many video games give us fascinating and complex stories that only get better the deeper you dive in. Here's some of our favorite video game lore.\nSubscribe for more: https://www.youtube.com/gameranxTV?sub_confirmation=1\n\n0:00 Intro \n0:23 The Dark Souls Series\n2:16 Mass Effect 1-3\n4:00 The Legend of Zelda\n5:52 The Witcher Series\n7:28 The Destiny Series\n8:46 Remedy Shared Universe\n10:06 The Nier Series\n11:42 The Kirby Series\n12:47 Bloodborne\n14:15 Elder Scrolls", "link": "https://www.youtube.com/watch?v=H6seZ2bYg8M", "date_published": "2022-01-17 00:00:00+00:00", "persistent": false, "user": null, "language": "en-US"}, {"source": "https://www.youtube.com/feeds/videos.xml?channel_id=UCNvzD7Z-g64bPXxGzaQaa4g", "title": "6 Video Games Series That Went DOWNHILL", "description": "We love video games, but some games series and franchises have disappointed us lately or fell out of public favor. Let's discuss a few of them.\nSubscribe for more: https://www.youtube.com/gameranxTV?sub_confirmation=1", "link": "https://www.youtube.com/watch?v=BP8i8J7dtmk", "date_published": "2022-01-16 00:00:00+00:00", "persistent": false, "user": null, "language": "en-US"}]