[{"source": "http://rss.nytimes.com/services/xml/rss/nyt/Technology.xml", "title": "She Worked for Twitter. Then She Tweeted at Elon Musk.", "description": "Sasha Solomon, a software engineer, joined others in the media business who lost their jobs this year after publicly taking on their employers.", "link": "https://www.nytimes.com/2022/12/23/style/she-worked-for-twitter-then-she-tweeted-at-elon-musk.html", "date_published": "2022-12-23 20:15:25+00:00", "persistent": false, "user": null, "language": "en-US"}, {"source": "http://rss.nytimes.com/services/xml/rss/nyt/Technology.xml", "title": "She Worked for Twitter. Then She Tweeted at Elon Musk.", "description": "Sasha Solomon, a software engineer, joined others in the media business who lost their jobs this year after publicly taking on their employers.", "link": "https://www.nytimes.com/2022/12/23/style/twitter-elon-musk-sasha-solomon.html", "date_published": "2022-12-23 20:15:25+00:00", "persistent": false, "user": null, "language": "en-US"}, {"source": "http://rss.nytimes.com/services/xml/rss/nyt/Technology.xml", "title": "What Happened to", "description": "The life cycle of a magical baby-soothing toy.", "link": "https://www.nytimes.com/2022/12/23/technology/beaming-buggie-baby-toy.html", "date_published": "2022-12-23 10:00:12+00:00", "persistent": false, "user": null, "language": "en-US"}]