[{"source": "https://www.youtube.com/feeds/videos.xml?channel_id=UCBJycsmduvYEL83R_U4JriQ", "title": "Google Pixel 7/Pro Review: Hard Problems? Software Answers!", "description": "Pixel 7 and Pixel 7 Pro are the smartest phones in the room. How far can that take them?\n\nSkin your Google Pixel 7 and 7 Pro at https://dbrand.com/pixel7\nThe hoodie! https://MKBHD.com\n\nGet the Google Pixel 7 Pro at https://geni.us/EM7Pt22 \nGet the Google Pixel 7 at https://geni.us/xC8XD \n\nTech I'm using right now: https://www.amazon.com/shop/MKBHD\n\nIntro Track: http://youtube.com/20syl\nPlaylist of MKBHD Intro music: https://goo.gl/B3AWV5\n\nPhone provided by Google for review.\n\n~\nhttp://twitter.com/MKBHD\nhttp://instagram.com/MKBHD\nhttp://facebook.com/MKBHD", "link": "https://www.youtube.com/watch?v=NE5H5intsck", "date_published": "2022-10-12 00:00:00+00:00", "persistent": false, "user": null, "language": "en-US"}]