[{"source": "https://www.youtube.com/feeds/videos.xml?channel_id=UCPKT_csvP72boVX0XrMtagQ", "title": "Hern\u00e1n Catt\u00e1neo at the Cercle Festival 2022 (A380 stage) in France", "description": "Hern\u00e1n Catt\u00e1neo playing an exclusive DJ set at the Cercle Festival 2022 (A380 stage), at the National Air & Space Museum of France, for Cercle.\n\n\u261e Support us and get access to exclusive videos & perks: https://Cercle.lnk.to/Patreon\n\u261e Listen to our playlists, tracks & sets: https://Cercle.lnk.to/Playlists\n\u261e Subscribe to our newsletter to know about our next shows: https://Cercle.lnk.to/Members\n\u261e Subscribe to our YouTube channel: https://Cercle.lnk.to/ytcercle\n\n\u261e Cercle Records \nHern\u00e1n Catt\u00e1neo, Mercurio - A380: http://cercle.lnk.to/hernancattaneoa380\n\n\u261e  Hern\u00e1n Catt\u00e1neo\nhttps://www.instagram.com/djhernancattaneo/\nhttps://open.spotify.com/artist/4mpJaw5y17CIN08qqe8EfB\nhttps://music.apple.com/us/artist/hern%C3%A1n-catt%C3%A1neo/44974489\n\n48\u00b056'55.6\"N 2\u00b026'03.7\"E\n\nVideo credits:\n\nArtist: Hern\u00e1n Catt\u00e1neo\nVenue: Cercle Festival 2022, National Air & Space Museum of France\nProduced by Cercle\nExecutive producers: Derek Barbolla, Philippe Tuchmann\nFilm directed by: Pol Souchier, Derek Barbolla\nDirector of photography:  Mathieu Glissant\nCameramen: Micka\u00ebl Fidjili, Quentin Souchier, Augustin Thai\nDrone pilot: Alexis Olas, J\u00e9r\u00e9mie Tridard\nFPV drone: Arthur Maneint, Kenny Dorion, Hensli Sage\nSound mastering: Antoine Guest \nProduction team: Ana\u00efs De Framond, Dan Aufseesser, Armand Prouh\u00e8ze, Tom Puippe\nCommunication: Pol Souchier, Lola Lebrati, Emie Monnier, Jeremy Maurin\nGraphic Design: Ana\u00eblle Rouquette\nLabel Assistant: Cl\u00e9mence Maillard\nTechnical Manager: Aur\u00e9lien Moisan\nChief Financial Officer: Andy Cheremond\nPost-production: Mathieu Glissant (Saison Unique Production)\nPhotographer: Maxime Chermat, Geoffrey Hubbel, Lily Rault \n______\n\nOfficial partners: \nNational Air & Space Museum of France\nMinist\u00e8re de la Culture \nDRAC \u00cele de France \nR\u00e9gion \u00cele de France\nSES Satellites \nW Hotels\nArianeGroup\n______\n\nSpecial thanks to:\nCruz Pereyra Lucena \nAlice Charbonnier \nTimoth\u00e9e Renard\nWilly Wargnier\nCarly Van Sickle \nStephane Viallon \nVincent Mathieu \nGuillaume Cabaret \nArthur Guerillon \nArnaud Fernandez \nVincent Merot\n\n______\n\nThis artistic performance has been recorded live.\n\nTracklist:\n00:00:00 Husa & Zeyada - On My Own (Hernan Cattaneo & Marcelo Vasami)\n00:06:30 Clyve Lights at Night\n00:11:52 Berni Turletti - Prana Vayu\n00:16:30 Kamilo Sanclemente -Spirals Inflections (Simply City Remix)\n00:22:00 Shai T - Oriki\n00:30:45 Verlk - hours go by\n00:37:11 BOg - Underwater (Hernan Cattaneo & Marcelo Vasami Remix)\n00:42:10 Sebastien Leger -Extassy\n00:48:50 Khen - Homeboy\n00:54:25 Axatipe - Back to the Roots\n01:01:30 Jody Barr - Eleanor\n01:06:00 Hernan Cattaneo & Mercurio-A380 (Cercle Records)\n01:10:54 Spencer Brown & Ezequiel Arias - Mad Rush\n01:15:30 Frederico Fioretti - Genesis\n01:20:25 Dabeat, Kamilo Sanclemente - Incense\n01:25:45 Kasey Taylor & Karl Pilbrow - Mount Epico\n01:30:16 Eric Lune - Predisposition\n01:37:40 Amadeo Acqua\n01:42:20 Navar - Herinneringen\n01:47:30 Apste - Magna\n1:51:02 Bottler - Tacoma (Gone Remix)\n1:55:19 Porra - See you\n\nFollow us on http://www.cercle.io", "link": "https://www.youtube.com/watch?v=Easqg4SUl2Q", "date_published": "2022-05-27 13:04:28+00:00", "persistent": false, "user": null, "language": "en-US"}]