[{"source": "http://feeds.bbci.co.uk/news/rss.xml", "title": "Students accuse lecturer of sharing Russia war lies", "description": "Academics have been criticised for spreading misinformation about the war in Ukraine on social media.", "link": "https://www.bbc.co.uk/news/education-61597405?at_medium=RSS&at_campaign=KARANGA", "date_published": "2022-05-30 23:42:16+00:00", "persistent": false, "user": null, "language": "en-US"}, {"source": "http://feeds.bbci.co.uk/news/rss.xml", "title": "Corby Pole Fair: The ancient celebration held once every 20 years", "description": "Nobody in Corby is certain as to exactly when the Pole Fair started or why it got its name.", "link": "https://www.bbc.co.uk/news/uk-england-northamptonshire-61442290?at_medium=RSS&at_campaign=KARANGA", "date_published": "2022-05-30 23:35:32+00:00", "persistent": false, "user": null, "language": "en-US"}, {"source": "http://feeds.bbci.co.uk/news/rss.xml", "title": "On board HMS Northumberland with ship's chaplain", "description": "HMS Northumberland's deployment changed considerably due to the Russian invasion of Ukraine.", "link": "https://www.bbc.co.uk/news/uk-61633940?at_medium=RSS&at_campaign=KARANGA", "date_published": "2022-05-30 23:09:47+00:00", "persistent": false, "user": null, "language": "en-US"}, {"source": "http://feeds.bbci.co.uk/news/rss.xml", "title": "Borgen: How the Danish political drama has been 'reinvented'", "description": "The series returns to Netflix this week, nearly a decade after its highly-praised original run.", "link": "https://www.bbc.co.uk/news/entertainment-arts-61591675?at_medium=RSS&at_campaign=KARANGA", "date_published": "2022-05-30 23:05:45+00:00", "persistent": false, "user": null, "language": "en-US"}, {"source": "http://feeds.bbci.co.uk/news/rss.xml", "title": "How India\u2019s first all-women newsroom is creating a media revolution", "description": "Khabar Lahariya is the first and only newsroom in India run entirely by women from marginalised backgrounds.", "link": "https://www.bbc.co.uk/news/world-asia-61587884?at_medium=RSS&at_campaign=KARANGA", "date_published": "2022-05-30 23:04:20+00:00", "persistent": false, "user": null, "language": "en-US"}, {"source": "http://feeds.bbci.co.uk/news/rss.xml", "title": "French Open: Rafael Nadal and Novak Djokovic set for Roland Garros quarter-final", "description": "Novak Djokovic says he is ready for the \"biggest challenge\" at the French Open when he plays 13-time champion Rafael Nadal in the quarter-finals.", "link": "https://www.bbc.co.uk/sport/tennis/61636755?at_medium=RSS&at_campaign=KARANGA", "date_published": "2022-05-30 20:00:22+00:00", "persistent": false, "user": null, "language": "en-US"}, {"source": "http://feeds.bbci.co.uk/news/rss.xml", "title": "Cultra beach find: 'Dad I just picked up a grenade. Is it real?'", "description": "Cole Chapman, who is 11, was out hunting for crabs when he picked up an unexploded grenade.", "link": "https://www.bbc.co.uk/news/uk-northern-ireland-61639584?at_medium=RSS&at_campaign=KARANGA", "date_published": "2022-05-30 18:47:47+00:00", "persistent": false, "user": null, "language": "en-US"}, {"source": "http://feeds.bbci.co.uk/news/rss.xml", "title": "Great British Bake Off winner Frances Quinn makes giant Jaffa Cake", "description": "A former Great British Bake Off winner has beaten her own giant Jaffa Cake record.", "link": "https://www.bbc.co.uk/news/uk-england-beds-bucks-herts-61638168?at_medium=RSS&at_campaign=KARANGA", "date_published": "2022-05-30 17:39:15+00:00", "persistent": false, "user": null, "language": "en-US"}, {"source": "http://feeds.bbci.co.uk/news/rss.xml", "title": "Champions League final: Fan videos of crowding and pepper spray", "description": "Footage from fans attending the Champions League final shows scenes of chaos.", "link": "https://www.bbc.co.uk/news/world-europe-61640126?at_medium=RSS&at_campaign=KARANGA", "date_published": "2022-05-30 17:30:11+00:00", "persistent": false, "user": null, "language": "en-US"}, {"source": "http://feeds.bbci.co.uk/news/rss.xml", "title": "'I watched from afar Russia\u2019s latest merciless assault on Severodonetsk'", "description": "Quentin Sommerville describes relentless artillery bombardment in Donbas ahead of Russian forces entering Severodonetsk.", "link": "https://www.bbc.co.uk/news/world-europe-61634050?at_medium=RSS&at_campaign=KARANGA", "date_published": "2022-05-30 16:18:21+00:00", "persistent": false, "user": null, "language": "en-US"}, {"source": "http://feeds.bbci.co.uk/news/rss.xml", "title": "Scot Tom Stoltman retains World's Strongest Man title", "description": "Tom Stoltman won the event days after travelling to Seville to see Rangers in the Europa League final.", "link": "https://www.bbc.co.uk/news/uk-scotland-highlands-islands-61632107?at_medium=RSS&at_campaign=KARANGA", "date_published": "2022-05-30 15:53:25+00:00", "persistent": false, "user": null, "language": "en-US"}, {"source": "http://feeds.bbci.co.uk/news/rss.xml", "title": "Half-term holiday plans in shreds as flights cancelled", "description": "Passengers are reporting being told at the flight gate that their trip has been cancelled.", "link": "https://www.bbc.co.uk/news/business-61630282?at_medium=RSS&at_campaign=KARANGA", "date_published": "2022-05-30 15:12:55+00:00", "persistent": false, "user": null, "language": "en-US"}, {"source": "http://feeds.bbci.co.uk/news/rss.xml", "title": "Mona Lisa: Man dressed as old woman throws cake at da Vinci painting", "description": "The perpetrator urged people to \"think of the earth\" while being led away from the scene.", "link": "https://www.bbc.co.uk/news/entertainment-arts-61635822?at_medium=RSS&at_campaign=KARANGA", "date_published": "2022-05-30 14:02:36+00:00", "persistent": false, "user": null, "language": "en-US"}, {"source": "http://feeds.bbci.co.uk/news/rss.xml", "title": "Men's U17 European Championship: Dutch 17-year-old Isaac Babadi scores Panenka penalty", "description": "Watch Netherlands' U17 captain Isaac Babadi calmly score a 'Panenka' penalty to win their shootout against Serbia and send the defending champions to the U17 European Championship final.", "link": "https://www.bbc.co.uk/sport/av/football/61636875?at_medium=RSS&at_campaign=KARANGA", "date_published": "2022-05-30 13:39:08+00:00", "persistent": false, "user": null, "language": "en-US"}, {"source": "http://feeds.bbci.co.uk/news/rss.xml", "title": "Platinum Jubilee: Charles and Camilla to join public for lunches", "description": "Prince Charles and Camilla will be celebrating the Queen's 70-year reign with members of the public.", "link": "https://www.bbc.co.uk/news/uk-61631944?at_medium=RSS&at_campaign=KARANGA", "date_published": "2022-05-30 12:50:43+00:00", "persistent": false, "user": null, "language": "en-US"}, {"source": "http://feeds.bbci.co.uk/news/rss.xml", "title": "Partygate: How much political danger is Boris Johnson in?", "description": "After the report into lockdown rule-breaking, political editor Chris Mason assesses the PM's future.", "link": "https://www.bbc.co.uk/news/uk-politics-61627796?at_medium=RSS&at_campaign=KARANGA", "date_published": "2022-05-30 12:11:29+00:00", "persistent": false, "user": null, "language": "en-US"}, {"source": "http://feeds.bbci.co.uk/news/rss.xml", "title": "Northern Ireland Protocol: Stormont meets as DUP is urged to back Speaker", "description": "The DUP says the recall is a \"stunt\" as there has been no progress on its NI Protocol demands.", "link": "https://www.bbc.co.uk/news/uk-northern-ireland-61627838?at_medium=RSS&at_campaign=KARANGA", "date_published": "2022-05-30 11:55:33+00:00", "persistent": false, "user": null, "language": "en-US"}, {"source": "http://feeds.bbci.co.uk/news/rss.xml", "title": "Emma Raducanu to begin Wimbledon preparations in Nottingham", "description": "Emma Raducanu brings forward the start of her grass-court season and will play at June's Nottingham Open.", "link": "https://www.bbc.co.uk/sport/tennis/61634648?at_medium=RSS&at_campaign=KARANGA", "date_published": "2022-05-30 11:41:31+00:00", "persistent": false, "user": null, "language": "en-US"}, {"source": "http://feeds.bbci.co.uk/news/rss.xml", "title": "Budget pasta prices jump 50% as food staples rise", "description": "Data reveals prices of some everyday items rose by 15% but the average increase is below inflation.", "link": "https://www.bbc.co.uk/news/business-61630281?at_medium=RSS&at_campaign=KARANGA", "date_published": "2022-05-30 11:32:22+00:00", "persistent": false, "user": null, "language": "en-US"}, {"source": "http://feeds.bbci.co.uk/news/rss.xml", "title": "Champions League final treatment was really traumatic, fan says", "description": "Suzanne Gower says what happened to Liverpool fans like her was \"dangerous\" and left her terrified.", "link": "https://www.bbc.co.uk/news/uk-england-merseyside-61632196?at_medium=RSS&at_campaign=KARANGA", "date_published": "2022-05-30 11:31:28+00:00", "persistent": false, "user": null, "language": "en-US"}, {"source": "http://feeds.bbci.co.uk/news/rss.xml", "title": "Woman tracks down her own stolen car before a police investigation", "description": "BBC research finds police are taking longer to attend serious offences and charging fewer suspects.", "link": "https://www.bbc.co.uk/news/uk-61592910?at_medium=RSS&at_campaign=KARANGA", "date_published": "2022-05-30 11:31:04+00:00", "persistent": false, "user": null, "language": "en-US"}, {"source": "http://feeds.bbci.co.uk/news/rss.xml", "title": "Champions League final: Fake tickets triggered Paris final chaos - France", "description": "The sports minister's comments come amid strong criticism of the policing of Saturday's Champions League final.", "link": "https://www.bbc.co.uk/news/world-europe-61630201?at_medium=RSS&at_campaign=KARANGA", "date_published": "2022-05-30 11:22:30+00:00", "persistent": false, "user": null, "language": "en-US"}, {"source": "http://feeds.bbci.co.uk/news/rss.xml", "title": "Che Adams: Scotland striker's nine-year rise from English seventh tier to Premier League", "description": "BBC Scotland charts striker Che Adams' nine-year rise from earning \u00a340 a week in the seventh tier to Premier League and international football.", "link": "https://www.bbc.co.uk/sport/football/61593615?at_medium=RSS&at_campaign=KARANGA", "date_published": "2022-05-30 10:54:26+00:00", "persistent": false, "user": null, "language": "en-US"}, {"source": "http://feeds.bbci.co.uk/news/rss.xml", "title": "Ukraine may soon get US long-range MLRS rocket system", "description": "The US looks set to send the weaponry, but Russia warns it would be a provocative escalation.", "link": "https://www.bbc.co.uk/news/world-europe-61627316?at_medium=RSS&at_campaign=KARANGA", "date_published": "2022-05-30 10:13:55+00:00", "persistent": false, "user": null, "language": "en-US"}, {"source": "http://feeds.bbci.co.uk/news/rss.xml", "title": "England v New Zealand: Matty Potts - from confident kid to the brink of his Test debut", "description": "From the confident kid fighting team-mates to the brink of a Test debut at Lord's, BBC Sport looks into the making of Matty Potts.", "link": "https://www.bbc.co.uk/sport/cricket/61604430?at_medium=RSS&at_campaign=KARANGA", "date_published": "2022-05-30 09:21:47+00:00", "persistent": false, "user": null, "language": "en-US"}, {"source": "http://feeds.bbci.co.uk/news/rss.xml", "title": "Ivan Perisic: Inter winger set for Tottenham medical", "description": "Inter winger Ivan Perisic is set to have a medical at Tottenham on Monday and is expected to join the club on a two-year deal.", "link": "https://www.bbc.co.uk/sport/football/61632388?at_medium=RSS&at_campaign=KARANGA", "date_published": "2022-05-30 09:05:28+00:00", "persistent": false, "user": null, "language": "en-US"}, {"source": "http://feeds.bbci.co.uk/news/rss.xml", "title": "Nancy Pelosi's husband Paul arrested for drink-driving", "description": "Paul Pelosi, the partner of the US House speaker, is bailed for $5,000 after a two-vehicle crash.", "link": "https://www.bbc.co.uk/news/world-us-canada-61631499?at_medium=RSS&at_campaign=KARANGA", "date_published": "2022-05-30 08:48:44+00:00", "persistent": false, "user": null, "language": "en-US"}, {"source": "http://feeds.bbci.co.uk/news/rss.xml", "title": "Top Gun: Maverick gives Tom Cruise first $100m opening weekend", "description": "Top Gun: Maverick is officially Tom Cruise's fastest-selling movie since War of the Worlds in 2005.", "link": "https://www.bbc.co.uk/news/entertainment-arts-61630131?at_medium=RSS&at_campaign=KARANGA", "date_published": "2022-05-30 08:42:23+00:00", "persistent": false, "user": null, "language": "en-US"}, {"source": "http://feeds.bbci.co.uk/news/rss.xml", "title": "Champions League final: BBC reporter describes his experience entering the stadium", "description": "Nick Parrott was among those trying to enter the Stade de France for the Champions League final.", "link": "https://www.bbc.co.uk/news/world-europe-61632206?at_medium=RSS&at_campaign=KARANGA", "date_published": "2022-05-30 08:41:23+00:00", "persistent": false, "user": null, "language": "en-US"}, {"source": "http://feeds.bbci.co.uk/news/rss.xml", "title": "Stevenage prom murder inquiry: Teen charged with killing Kajetan Migdal", "description": "Kajetan Migdal dies from his injuries after an attack while on his way home from a school prom.", "link": "https://www.bbc.co.uk/news/uk-england-beds-bucks-herts-61629545?at_medium=RSS&at_campaign=KARANGA", "date_published": "2022-05-30 08:22:19+00:00", "persistent": false, "user": null, "language": "en-US"}, {"source": "http://feeds.bbci.co.uk/news/rss.xml", "title": "Ukraine war: Russian Foreign Minister Lavrov denies Putin illness", "description": "Sergei Lavrov says the Russian president appears in public daily and no sane person would think him ill.", "link": "https://www.bbc.co.uk/news/world-europe-61628473?at_medium=RSS&at_campaign=KARANGA", "date_published": "2022-05-30 07:59:59+00:00", "persistent": false, "user": null, "language": "en-US"}, {"source": "http://feeds.bbci.co.uk/news/rss.xml", "title": "Miscarriage: 'We had to put baby\u2019s remains in fridge'", "description": "A couple who lost their baby say staff had no idea what to do for them when they arrived at A&amp;E.", "link": "https://www.bbc.co.uk/news/health-61576787?at_medium=RSS&at_campaign=KARANGA", "date_published": "2022-05-30 05:05:20+00:00", "persistent": false, "user": null, "language": "en-US"}, {"source": "http://feeds.bbci.co.uk/news/rss.xml", "title": "Ukraine war student-turned-soldier: 'Friends die in your arms'", "description": "After trading university for combat in Kyiv, the young soldier is in the thick of fighting in Donbas.", "link": "https://www.bbc.co.uk/news/world-europe-61624557?at_medium=RSS&at_campaign=KARANGA", "date_published": "2022-05-30 05:01:36+00:00", "persistent": false, "user": null, "language": "en-US"}, {"source": "http://feeds.bbci.co.uk/news/rss.xml", "title": "Newspaper headlines: 'Bonfire of EU laws' and millions face power cuts", "description": "Plans to axe dozens of EU laws, and gas shortages caused by the Ukraine war, lead the papers.", "link": "https://www.bbc.co.uk/news/blogs-the-papers-61628399?at_medium=RSS&at_campaign=KARANGA", "date_published": "2022-05-30 04:27:44+00:00", "persistent": false, "user": null, "language": "en-US"}, {"source": "http://feeds.bbci.co.uk/news/rss.xml", "title": "Cost of living crisis: Relying on food handouts and moving country", "description": "People from Italy, Brazil, Ghana, Thailand and New Zealand discuss the impact of the cost of living crisis.", "link": "https://www.bbc.co.uk/news/world-61584608?at_medium=RSS&at_campaign=KARANGA", "date_published": "2022-05-30 01:20:20+00:00", "persistent": false, "user": null, "language": "en-US"}, {"source": "http://feeds.bbci.co.uk/news/rss.xml", "title": "Peterborough school counsellor tells of her anorexia journey", "description": "Shama Hanif tells of her her struggle with anorexia and how she has cast off the shame she once felt.", "link": "https://www.bbc.co.uk/news/uk-england-cambridgeshire-61549815?at_medium=RSS&at_campaign=KARANGA", "date_published": "2022-05-30 00:40:53+00:00", "persistent": false, "user": null, "language": "en-US"}, {"source": "http://feeds.bbci.co.uk/news/rss.xml", "title": "Platinum Jubilee: The Queen has sought to be nation's comforter-in-chief", "description": "The BBC's Mark Easton looks at how the Queen has repeatedly sought to make change easier.", "link": "https://www.bbc.co.uk/news/uk-61579068?at_medium=RSS&at_campaign=KARANGA", "date_published": "2022-05-30 00:37:51+00:00", "persistent": false, "user": null, "language": "en-US"}]