[{"source": "https://www.youtube.com/feeds/videos.xml?channel_id=UCswH8ovgUp5Bdg-0_JTYFNw", "title": "You\u2019ve Gotta Be F*cking Kidding Me", "description": "As Joe Biden accidentally reveals a \u2018cheat sheet\u2019 and Nancy Pelosi appears to elbow a child in the ribs, we ask, how do your elected leaders even get out of bed in the morning, let alone run a country? #biden #pelosi #democrats\n\nReferences\nhttps://www.independent.co.uk/news/world/americas/us-politics/joe-biden-cheat-sheet-notes-putin-b2108539.html\nhttps://nypost.com/2022/06/27/gop-rep-mayra-flores-accuses-speaker-nancy-pelosi-of-pushing-daughter-during-photo-op/\nhttps://nypost.com/2022/06/23/a-very-specific-cheat-sheet-reminds-biden-how-to-act/\n--------------------------------------------------------------------------------------------------------------------------\nTickets now on sale for my 1 day event COMMUNITY in Hay-on-Wye. I'm joined by Wim, Vandana Shiva for conversations on spirituality, wellness, healthy living and our environment. Get your tickets bit.ly/3xoHQPv\n\nJoin Our Community HERE: https://www.russellbrand.com/join \n\nTo listen, subscribe to the Luminary Channel on Apple Podcasts at apple.co/russell or on the Luminary app http://luminary.link/russell\n\nFor meditation and breath work, subscribe to my side-channel: \nhttps://www.youtube.com/c/AwakeningWithRussell\n\nMy Weekly meditation podcast, Above the Noise, is available now on Apple & Luminary\nhttp://apple.co/meditate\nhttp://luminary.link/meditate\n\nRumble:\nhttps://rumble.com/c/russellbrand\n\nLocals:\nhttps://russellbrand.locals.com/", "link": "https://www.youtube.com/watch?v=j1taAqON5vY", "date_published": "2022-06-28 00:00:00+00:00", "persistent": false, "user": null, "language": "en-US"}, {"source": "https://www.youtube.com/feeds/videos.xml?channel_id=UCswH8ovgUp5Bdg-0_JTYFNw", "title": "Roe v Wade: You Need To Know This Now", "description": "The US Supreme Court last week ruled to overturn Roe v. Wade. But what do Americans really think about abortion, and has it always been such a partisan issue or is it just another example of politicians using a complex situation for their own gain?  \n#roevwade #supremecourt \n\nReferences\nhttps://www.reuters.com/world/us/how-abortion-became-divisive-issue-us-politics-2022-06-24/\n--------------------------------------------------------------------------------------------------------------------------\nTickets now on sale for my 1 day event COMMUNITY in Hay-on-Wye. I'm joined by Wim, Vandana Shiva for conversations on spirituality, wellness, healthy living and our environment. Get your tickets bit.ly/3xoHQPv\n\nJoin Our Community HERE: https://www.russellbrand.com/join \n\nTo listen, subscribe to the Luminary Channel on Apple Podcasts at apple.co/russell or on the Luminary app http://luminary.link/russell\n\nFor meditation and breath work, subscribe to my side-channel: \nhttps://www.youtube.com/c/AwakeningWithRussell\n\nMy Weekly meditation podcast, Above the Noise, is available now on Apple & Luminary\nhttp://apple.co/meditate\nhttp://luminary.link/meditate\n\nRumble:\nhttps://rumble.com/c/russellbrand\n\nLocals:\nhttps://russellbrand.locals.com/", "link": "https://www.youtube.com/watch?v=ZGsFrk0MrwQ", "date_published": "2022-06-27 00:00:00+00:00", "persistent": false, "user": null, "language": "en-US"}]