{"entries": [{"source": "https://www.wired.com/feed/category/business/latest/rss", "link": "https://www.wired.com/story/amazons-new-robot-sparrow-can-handle-most-items-in-the-everything-store/", "title": "Amazon\u2019s New Robot Sparrow Can Handle Most Items in the Everything Store", "date_published": "2022-11-10 21:33:57+00:00", "description": "Sparrow could shift the balance between humans and machines in the company\u2019s warehouses, using machine learning algorithms and a custom gripper.", "persistent": false, "language": "en-US"}, {"source": "https://www.wired.com/feed/category/business/latest/rss", "link": "https://www.wired.com/story/meta-layoffs-overhiring/", "title": "The Reason for Meta\u2019s Massive Layoffs? Ghosts in the Machine", "date_published": "2022-11-10 16:28:54+00:00", "description": "The social media company's failed projects required thousands of staffers who swelled the ranks and never left.", "persistent": false, "language": "en-US"}, {"source": "https://www.wired.com/feed/category/business/latest/rss", "link": "https://www.wired.com/story/twitter-blue-check-verification-buy-scams/", "title": "Elon Musk's Twitter Blue Verification Is a Gift to Scammers", "date_published": "2022-11-10 16:25:20+00:00", "description": "Anyone can get a blue tick on Twitter without proving who they are. And it\u2019s already causing a ton of problems.", "persistent": false, "language": "en-US"}, {"source": "https://www.wired.com/feed/category/business/latest/rss", "link": "https://www.wired.com/story/makerdao-rune-christensen-decentralize/", "title": "This Billion-Dollar Crypto Collective Is Tearing Itself Apart", "date_published": "2022-11-10 12:00:00+00:00", "description": "One of the world\u2019s biggest crypto groups just voted to back its enigmatic founder. The only problem is, no one understands his plan.", "persistent": false, "language": "en-US"}], "source": {"url": "https://www.wired.com/feed/category/business/latest/rss", "title": "Wired business"}}