[{"source": "https://theprint.in", "title": "Journalists in Europe are getting attacked for covering anti-lockdown, anti-vaccine protests", "description": "Journalists in Europe are getting attacked for covering anti-lockdown, anti-vaccine protests", "link": "https://theprint.in/world/journalists-in-europe-are-getting-attacked-for-covering-anti-lockdown-anti-vaccine-protests/797005/", "date_published": "2022-01-08 20:49:56+00:00", "persistent": true, "user": "rumpel", "language": "en", "tags": ["media", "lockdown", "big brother", "covid"]}]