[{"source": "https://www.youtube.com/feeds/videos.xml?channel_id=UCzQUP1qoWDoEbmsQxvdjxgQ", "title": "Does Weight Cutting Give Fighters Eating Disorders?", "description": "Taken from JRE MMA Show #133 w/\"Sugar\" Sean O'Malley:\nhttps://open.spotify.com/episode/52DFy29uKI8tC0Wc9eQ64N?si=9ef608a57ccb45bf", "link": "https://www.youtube.com/watch?v=rtr0V254akc", "date_published": "2022-11-24 00:00:00+00:00", "persistent": false, "user": null, "language": "en-US"}, {"source": "https://www.youtube.com/feeds/videos.xml?channel_id=UCzQUP1qoWDoEbmsQxvdjxgQ", "title": "Joe Remembers Anthony \"Rumble\" Johnson", "description": "Taken from JRE MMA Show #133 w/\"Sugar\" Sean O'Malley:\nhttps://open.spotify.com/episode/52DFy29uKI8tC0Wc9eQ64N?si=9ef608a57ccb45bf", "link": "https://www.youtube.com/watch?v=S8S1KKGLCqE", "date_published": "2022-11-24 00:00:00+00:00", "persistent": false, "user": null, "language": "en-US"}, {"source": "https://www.youtube.com/feeds/videos.xml?channel_id=UCzQUP1qoWDoEbmsQxvdjxgQ", "title": "Danny Brown on The Downside of Rap", "description": "Taken from JRE #1902 w/Danny Brown:\nhttps://open.spotify.com/episode/2auNrZZKoraDKSE74SpLR6?si=fcd674945a5f4a86", "link": "https://www.youtube.com/watch?v=tCTpie2xivQ", "date_published": "2022-11-23 00:00:00+00:00", "persistent": false, "user": null, "language": "en-US"}]