[{"source": "https://pulsmedycyny.pl", "title": "Prof. Horban o ma\u0142opolskiej kurator o\u015bwiaty: powinna zosta\u0107 zdymisjonowana - Puls Medycyny - pulsmedycyny.pl", "description": "Prof. Horban o ma\u0142opolskiej kurator o\u015bwiaty: powinna zosta\u0107 zdymisjonowana - Puls Medycyny - pulsmedycyny.pl", "link": "https://pulsmedycyny.pl/prof-horban-o-malopolskiej-kurator-oswiaty-powinna-zostac-zdymisjonowana-1138380", "date_published": "2022-01-12 07:42:25+00:00", "persistent": true, "user": "rumpel", "language": "pl", "tags": ["propaganda", "covid", "censorship"]}]