[{"source": "https://www.youtube.com/feeds/videos.xml?channel_id=UCDVb4m_5QHhZElT47E1oODg", "title": "Hollywood 2022: Get Woke, Lose a Lot of Money!", "description": "Support my work on Subscribe Star: https://www.subscribestar.com/dave-cullen\nFollow me on Bitchute: https://www.bitchute.com/channel/hybM74uIHJKg/\n\nSource article: https://www.breitbart.com/entertainment/2022/12/25/hollywood-lost-more-than-500-billion-in-market-value-in-2022/\n\nKEEP UP ON SOCIAL MEDIA:\nGab: https://gab.ai/DaveCullen\nSubscribe on Gab TV: https://tv.gab.com/channel/DaveCullen\nMinds.com: https://www.minds.com/davecullen\nSubscribe on Odysee: https://odysee.com/@TheDaveCullenShow:7", "link": "https://www.youtube.com/watch?v=KvXqSF_WS2c", "date_published": "2022-12-31 18:44:46+00:00", "persistent": false, "user": null, "language": "en-US"}]