[{"source": "https://www.youtube.com/feeds/videos.xml?channel_id=UCswH8ovgUp5Bdg-0_JTYFNw", "title": "\u201cWe Don\u2019t Live In A Democracy\u201d Blacklisted Journalist Matt Kennard", "description": "Matt Kennard is a London based author and journalist. He is head of investigations at the\u00a0investigative journalism\u00a0website\u00a0Declassified UK. He explains in his new book how corporations overthrew democracy. Do you agree? #amazon #corporation #democrats \n--------------------------------------------------------------------------------------------------------------------------\nFOLLOW and WATCH me LIVE weekdays on Rumble https://rumble.com/russellbrand\n\nJoin The Community STAY FREE AF: https://russellbrand.locals.com/\n\nCome to My Festival COMMUNITY - https://www.russellbrand.com/community-2023/\nNEW MERCH! https://stuff.russellbrand.com/", "link": "https://www.youtube.com/watch?v=i2DnEb96xPc", "date_published": "2022-12-11 00:00:00+00:00", "persistent": false, "user": null, "language": "en-US"}, {"source": "https://www.youtube.com/feeds/videos.xml?channel_id=UCswH8ovgUp5Bdg-0_JTYFNw", "title": "Who REALLY Controlled The Pandemic?!", "description": "Adam Wagner, the author of Emergency State explained to us how the UK Government was able to bypass democratic process to introduce new pandemic laws. #covid #pandemic #lockdowns\n--------------------------------------------------------------------------------------------------------------------------\nFOLLOW and WATCH me LIVE weekdays on Rumble https://rumble.com/russellbrand\n\nJoin The Community STAY FREE AF: https://russellbrand.locals.com/\n\nCome to My Festival COMMUNITY - https://www.russellbrand.com/community-2023/\nNEW MERCH! https://stuff.russellbrand.com/", "link": "https://www.youtube.com/watch?v=YmAkCNeZw6U", "date_published": "2022-12-10 00:00:00+00:00", "persistent": false, "user": null, "language": "en-US"}]