[{"source": "https://nypost.com", "title": "Woke comic books are laughable money-losers \u2014 but DC, Marvel push them", "description": "Woke comic books are laughable money-losers \u2014 but DC, Marvel push them", "link": "https://nypost.com/2022/12/27/woke-comic-books-are-laughable-money-losers-but-dc-marvel-push-them/", "date_published": "2022-12-27 06:58:11+00:00", "persistent": true, "user": "rumpel", "language": "en-US", "tags": ["go woke go broke", "lgbt", "indoctrination", "the left wing", "comics"]}]